Workbook

Sheet Data Sheet
A1: Sku | B1: Style Code | C1: Colour Code | D1: Option | E1: Category | F1: Material | G1: Style | H1: Range | I1: Colour | J1: Size | K1: Description | L1: Quantity Avilable | M1: Landed Cost Price | N1: Agreed GBP RRP | O1: Vat | P1: Net RRP | Q1: Margin | R1: Original Description (raw, unedited - for reference)
A2: 900000ZZAUBE0000 | B2: 900000 | C2: AUBE | D2: 900196AUBE | E2: Fingerless Gloves | F2: Cashmere | G2: Cashmere Fingerless Gloves | H2: Core | I2: Aubergine | J2: One Size | K2: Cashmere Fingerless Gloves Aubergine | L2: 0 | M2: 6.95 | N2: 39 | O2: 1.2 | P2: =SUM(N2/O2) | Q2: =((N2/O2)-M2)/(N2/O2) | R2: Cashmere Fingerless Gloves Aubergine
A3: 900236ZZBLCK0000 | B3: =VALUE(LEFT(A3,6)) -> 900236 | C3: =MID(A3,9,4) -> BLCK | D3: =B3&C3 -> 900236BLCK | E3: =VLOOKUP(B3,Lookup!$A$2:$G$7,2,FALSE) -> Fingerless Gloves | F3: =VLOOKUP(B3,Lookup!$A$2:$G$7,3,FALSE) -> Cashmere | G3: ="Cashmere "&E3 -> Cashmere Fingerless Gloves | H3: TBC | I3: =TRIM(MID(R3,FIND(",",R3)+1,FIND(",",R3,FIND(",",R3)+1)-FIND(",",R3)-1)) -> Black | J3: One Size | K3: =VLOOKUP(B3,Lookup!$A$2:$G$7,4,FALSE)&", "&I3&", O/S" -> Re:Born Cashmere Fingerless Gloves, Black, O/S | L3: 6600 | M3: =VLOOKUP(B3,Lookup!$A$2:$G$7,5,FALSE) -> 8.2 | N3: =VLOOKUP(B3,Lookup!$A$2:$G$7,6,FALSE) -> 39 | O3: =VLOOKUP(B3,Lookup!$A$2:$G$7,7,FALSE) -> 1.2 | P3: =IF(AND(ISNUMBER(N3),ISNUMBER(O3)),N3/O3,"TBC") -> 32.5 | Q3: =IF(AND(ISNUMBER(N3),ISNUMBER(O3),ISNUMBER(M3)),((N3/O3)-M3)/(N3/O3),"TBC") -> 0.74769231 | R3: Re:Born Cashmere Fingerless Gloves, Black, O/S
A4: 900236ZZLGRY0000 | B4: =VALUE(LEFT(A4,6)) -> 900236 | C4: =MID(A4,9,4) -> LGRY | D4: =B4&C4 -> 900236LGRY | E4: =VLOOKUP(B4,Lookup!$A$2:$G$7,2,FALSE) -> Fingerless Gloves | F4: =VLOOKUP(B4,Lookup!$A$2:$G$7,3,FALSE) -> Cashmere | G4: ="Cashmere "&E4 -> Cashmere Fingerless Gloves | H4: TBC | I4: =TRIM(MID(R4,FIND(",",R4)+1,FIND(",",R4,FIND(",",R4)+1)-FIND(",",R4)-1)) -> Light Grey | J4: One Size | K4: =VLOOKUP(B4,Lookup!$A$2:$G$7,4,FALSE)&", "&I4&", O/S" -> Re:Born Cashmere Fingerless Gloves, Light Grey, O/S | L4: 3605 | M4: =VLOOKUP(B4,Lookup!$A$2:$G$7,5,FALSE) -> 8.2 | N4: =VLOOKUP(B4,Lookup!$A$2:$G$7,6,FALSE) -> 39 | O4: =VLOOKUP(B4,Lookup!$A$2:$G$7,7,FALSE) -> 1.2 | P4: =IF(AND(ISNUMBER(N4),ISNUMBER(O4)),N4/O4,"TBC") -> 32.5 | Q4: =IF(AND(ISNUMBER(N4),ISNUMBER(O4),ISNUMBER(M4)),((N4/O4)-M4)/(N4/O4),"TBC") -> 0.74769231 | R4: Re:Born Cashmere Fingerless Gloves, Light Grey, O/S
A5: 900236ZZDKGR0000 | B5: =VALUE(LEFT(A5,6)) -> 900236 | C5: =MID(A5,9,4) -> DKGR | D5: =B5&C5 -> 900236DKGR | E5: =VLOOKUP(B5,Lookup!$A$2:$G$7,2,FALSE) -> Fingerless Gloves | F5: =VLOOKUP(B5,Lookup!$A$2:$G$7,3,FALSE) -> Cashmere | G5: ="Cashmere "&E5 -> Cashmere Fingerless Gloves | H5: TBC | I5: =TRIM(MID(R5,FIND(",",R5)+1,FIND(",",R5,FIND(",",R5)+1)-FIND(",",R5)-1)) -> Dark Grey | J5: One Size | K5: =VLOOKUP(B5,Lookup!$A$2:$G$7,4,FALSE)&", "&I5&", O/S" -> Re:Born Cashmere Fingerless Gloves, Dark Grey, O/S | L5: 3599 | M5: =VLOOKUP(B5,Lookup!$A$2:$G$7,5,FALSE) -> 8.2 | N5: =VLOOKUP(B5,Lookup!$A$2:$G$7,6,FALSE) -> 39 | O5: =VLOOKUP(B5,Lookup!$A$2:$G$7,7,FALSE) -> 1.2 | P5: =IF(AND(ISNUMBER(N5),ISNUMBER(O5)),N5/O5,"TBC") -> 32.5 | Q5: =IF(AND(ISNUMBER(N5),ISNUMBER(O5),ISNUMBER(M5)),((N5/O5)-M5)/(N5/O5),"TBC") -> 0.74769231 | R5: Re:Born Cashmere Fingerless Gloves, Dark Grey, O/S
A6: 900236ZZLLBL0000 | B6: =VALUE(LEFT(A6,6)) -> 900236 | C6: =MID(A6,9,4) -> LLBL | D6: =B6&C6 -> 900236LLBL | E6: =VLOOKUP(B6,Lookup!$A$2:$G$7,2,FALSE) -> Fingerless Gloves | F6: =VLOOKUP(B6,Lookup!$A$2:$G$7,3,FALSE) -> Cashmere | G6: ="Cashmere "&E6 -> Cashmere Fingerless Gloves | H6: TBC | I6: =TRIM(MID(R6,FIND(",",R6)+1,FIND(",",R6,FIND(",",R6)+1)-FIND(",",R6)-1)) -> Light Beige | J6: One Size | K6: =VLOOKUP(B6,Lookup!$A$2:$G$7,4,FALSE)&", "&I6&", O/S" -> Re:Born Cashmere Fingerless Gloves, Light Beige, O/S | L6: 3018 | M6: =VLOOKUP(B6,Lookup!$A$2:$G$7,5,FALSE) -> 8.2 | N6: =VLOOKUP(B6,Lookup!$A$2:$G$7,6,FALSE) -> 39 | O6: =VLOOKUP(B6,Lookup!$A$2:$G$7,7,FALSE) -> 1.2 | P6: =IF(AND(ISNUMBER(N6),ISNUMBER(O6)),N6/O6,"TBC") -> 32.5 | Q6: =IF(AND(ISNUMBER(N6),ISNUMBER(O6),ISNUMBER(M6)),((N6/O6)-M6)/(N6/O6),"TBC") -> 0.74769231 | R6: Re:Born Cashmere Fingerless Gloves, Light Beige, O/S
A7: 900236ZZLTBR0000 | B7: =VALUE(LEFT(A7,6)) -> 900236 | C7: =MID(A7,9,4) -> LTBR | D7: =B7&C7 -> 900236LTBR | E7: =VLOOKUP(B7,Lookup!$A$2:$G$7,2,FALSE) -> Fingerless Gloves | F7: =VLOOKUP(B7,Lookup!$A$2:$G$7,3,FALSE) -> Cashmere | G7: ="Cashmere "&E7 -> Cashmere Fingerless Gloves | H7: TBC | I7: =TRIM(MID(R7,FIND(",",R7)+1,FIND(",",R7,FIND(",",R7)+1)-FIND(",",R7)-1)) -> Light Brown | J7: One Size | K7: =VLOOKUP(B7,Lookup!$A$2:$G$7,4,FALSE)&", "&I7&", O/S" -> Re:Born Cashmere Fingerless Gloves, Light Brown, O/S | L7: 1302 | M7: =VLOOKUP(B7,Lookup!$A$2:$G$7,5,FALSE) -> 8.2 | N7: =VLOOKUP(B7,Lookup!$A$2:$G$7,6,FALSE) -> 39 | O7: =VLOOKUP(B7,Lookup!$A$2:$G$7,7,FALSE) -> 1.2 | P7: =IF(AND(ISNUMBER(N7),ISNUMBER(O7)),N7/O7,"TBC") -> 32.5 | Q7: =IF(AND(ISNUMBER(N7),ISNUMBER(O7),ISNUMBER(M7)),((N7/O7)-M7)/(N7/O7),"TBC") -> 0.74769231 | R7: Re:Born Cashmere Fingerless Gloves, Light Brown, O/S
A8: 900236ZZNAVY0000 | B8: =VALUE(LEFT(A8,6)) -> 900236 | C8: =MID(A8,9,4) -> NAVY | D8: =B8&C8 -> 900236NAVY | E8: =VLOOKUP(B8,Lookup!$A$2:$G$7,2,FALSE) -> Fingerless Gloves | F8: =VLOOKUP(B8,Lookup!$A$2:$G$7,3,FALSE) -> Cashmere | G8: ="Cashmere "&E8 -> Cashmere Fingerless Gloves | H8: TBC | I8: =TRIM(MID(R8,FIND(",",R8)+1,FIND(",",R8,FIND(",",R8)+1)-FIND(",",R8)-1)) -> Navy | J8: One Size | K8: =VLOOKUP(B8,Lookup!$A$2:$G$7,4,FALSE)&", "&I8&", O/S" -> Re:Born Cashmere Fingerless Gloves, Navy, O/S | L8: 1036 | M8: =VLOOKUP(B8,Lookup!$A$2:$G$7,5,FALSE) -> 8.2 | N8: =VLOOKUP(B8,Lookup!$A$2:$G$7,6,FALSE) -> 39 | O8: =VLOOKUP(B8,Lookup!$A$2:$G$7,7,FALSE) -> 1.2 | P8: =IF(AND(ISNUMBER(N8),ISNUMBER(O8)),N8/O8,"TBC") -> 32.5 | Q8: =IF(AND(ISNUMBER(N8),ISNUMBER(O8),ISNUMBER(M8)),((N8/O8)-M8)/(N8/O8),"TBC") -> 0.74769231 | R8: Re:Born Cashmere Fingerless Gloves, Navy, O/S
A9: 900236ZZLMLL0000 | B9: =VALUE(LEFT(A9,6)) -> 900236 | C9: =MID(A9,9,4) -> LMLL | D9: =B9&C9 -> 900236LMLL | E9: =VLOOKUP(B9,Lookup!$A$2:$G$7,2,FALSE) -> Fingerless Gloves | F9: =VLOOKUP(B9,Lookup!$A$2:$G$7,3,FALSE) -> Cashmere | G9: ="Cashmere "&E9 -> Cashmere Fingerless Gloves | H9: TBC | I9: =TRIM(MID(R9,FIND(",",R9)+1,FIND(",",R9,FIND(",",R9)+1)-FIND(",",R9)-1)) -> Light Maroon | J9: One Size | K9: =VLOOKUP(B9,Lookup!$A$2:$G$7,4,FALSE)&", "&I9&", O/S" -> Re:Born Cashmere Fingerless Gloves, Light Maroon, O/S | L9: 991 | M9: =VLOOKUP(B9,Lookup!$A$2:$G$7,5,FALSE) -> 8.2 | N9: =VLOOKUP(B9,Lookup!$A$2:$G$7,6,FALSE) -> 39 | O9: =VLOOKUP(B9,Lookup!$A$2:$G$7,7,FALSE) -> 1.2 | P9: =IF(AND(ISNUMBER(N9),ISNUMBER(O9)),N9/O9,"TBC") -> 32.5 | Q9: =IF(AND(ISNUMBER(N9),ISNUMBER(O9),ISNUMBER(M9)),((N9/O9)-M9)/(N9/O9),"TBC") -> 0.74769231 | R9: Re:Born Cashmere Fingerless Gloves, Light Maroon, O/S
A10: 900236ZZRDST0000 | B10: =VALUE(LEFT(A10,6)) -> 900236 | C10: =MID(A10,9,4) -> RDST | D10: =B10&C10 -> 900236RDST | E10: =VLOOKUP(B10,Lookup!$A$2:$G$7,2,FALSE) -> Fingerless Gloves | F10: =VLOOKUP(B10,Lookup!$A$2:$G$7,3,FALSE) -> Cashmere | G10: ="Cashmere "&E10 -> Cashmere Fingerless Gloves | H10: TBC | I10: =TRIM(MID(R10,FIND(",",R10)+1,FIND(",",R10,FIND(",",R10)+1)-FIND(",",R10)-1)) -> Red | J10: One Size | K10: =VLOOKUP(B10,Lookup!$A$2:$G$7,4,FALSE)&", "&I10&", O/S" -> Re:Born Cashmere Fingerless Gloves, Red, O/S | L10: 988 | M10: =VLOOKUP(B10,Lookup!$A$2:$G$7,5,FALSE) -> 8.2 | N10: =VLOOKUP(B10,Lookup!$A$2:$G$7,6,FALSE) -> 39 | O10: =VLOOKUP(B10,Lookup!$A$2:$G$7,7,FALSE) -> 1.2 | P10: =IF(AND(ISNUMBER(N10),ISNUMBER(O10)),N10/O10,"TBC") -> 32.5 | Q10: =IF(AND(ISNUMBER(N10),ISNUMBER(O10),ISNUMBER(M10)),((N10/O10)-M10)/(N10/O10),"TBC") -> 0.74769231 | R10: Re:Born Cashmere Fingerless Gloves, Red, O/S
A11: 900236ZZAAAC0000 | B11: =VALUE(LEFT(A11,6)) -> 900236 | C11: =MID(A11,9,4) -> AAAC | D11: =B11&C11 -> 900236AAAC | E11: =VLOOKUP(B11,Lookup!$A$2:$G$7,2,FALSE) -> Fingerless Gloves | F11: =VLOOKUP(B11,Lookup!$A$2:$G$7,3,FALSE) -> Cashmere | G11: ="Cashmere "&E11 -> Cashmere Fingerless Gloves | H11: TBC | I11: =TRIM(MID(R11,FIND(",",R11)+1,FIND(",",R11,FIND(",",R11)+1)-FIND(",",R11)-1)) -> Baby Pink | J11: One Size | K11: =VLOOKUP(B11,Lookup!$A$2:$G$7,4,FALSE)&", "&I11&", O/S" -> Re:Born Cashmere Fingerless Gloves, Baby Pink, O/S | L11: 800 | M11: =VLOOKUP(B11,Lookup!$A$2:$G$7,5,FALSE) -> 8.2 | N11: =VLOOKUP(B11,Lookup!$A$2:$G$7,6,FALSE) -> 39 | O11: =VLOOKUP(B11,Lookup!$A$2:$G$7,7,FALSE) -> 1.2 | P11: =IF(AND(ISNUMBER(N11),ISNUMBER(O11)),N11/O11,"TBC") -> 32.5 | Q11: =IF(AND(ISNUMBER(N11),ISNUMBER(O11),ISNUMBER(M11)),((N11/O11)-M11)/(N11/O11),"TBC") -> 0.74769231 | R11: Re:Born Cashmere Fingerless Gloves, Baby Pink, O/S
A12: 900236ZZDKBR0000 | B12: =VALUE(LEFT(A12,6)) -> 900236 | C12: =MID(A12,9,4) -> DKBR | D12: =B12&C12 -> 900236DKBR | E12: =VLOOKUP(B12,Lookup!$A$2:$G$7,2,FALSE) -> Fingerless Gloves | F12: =VLOOKUP(B12,Lookup!$A$2:$G$7,3,FALSE) -> Cashmere | G12: ="Cashmere "&E12 -> Cashmere Fingerless Gloves | H12: TBC | I12: =TRIM(MID(R12,FIND(",",R12)+1,FIND(",",R12,FIND(",",R12)+1)-FIND(",",R12)-1)) -> Dark Brown | J12: One Size | K12: =VLOOKUP(B12,Lookup!$A$2:$G$7,4,FALSE)&", "&I12&", O/S" -> Re:Born Cashmere Fingerless Gloves, Dark Brown, O/S | L12: 740 | M12: =VLOOKUP(B12,Lookup!$A$2:$G$7,5,FALSE) -> 8.2 | N12: =VLOOKUP(B12,Lookup!$A$2:$G$7,6,FALSE) -> 39 | O12: =VLOOKUP(B12,Lookup!$A$2:$G$7,7,FALSE) -> 1.2 | P12: =IF(AND(ISNUMBER(N12),ISNUMBER(O12)),N12/O12,"TBC") -> 32.5 | Q12: =IF(AND(ISNUMBER(N12),ISNUMBER(O12),ISNUMBER(M12)),((N12/O12)-M12)/(N12/O12),"TBC") -> 0.74769231 | R12: Re:Born Cashmere Fingerless Gloves, Dark Brown, O/S
A13: 900236ZZYELL0000 | B13: =VALUE(LEFT(A13,6)) -> 900236 | C13: =MID(A13,9,4) -> YELL | D13: =B13&C13 -> 900236YELL | E13: =VLOOKUP(B13,Lookup!$A$2:$G$7,2,FALSE) -> Fingerless Gloves | F13: =VLOOKUP(B13,Lookup!$A$2:$G$7,3,FALSE) -> Cashmere | G13: ="Cashmere "&E13 -> Cashmere Fingerless Gloves | H13: TBC | I13: =TRIM(MID(R13,FIND(",",R13)+1,FIND(",",R13,FIND(",",R13)+1)-FIND(",",R13)-1)) -> Yellow | J13: One Size | K13: =VLOOKUP(B13,Lookup!$A$2:$G$7,4,FALSE)&", "&I13&", O/S" -> Re:Born Cashmere Fingerless Gloves, Yellow, O/S | L13: 736 | M13: =VLOOKUP(B13,Lookup!$A$2:$G$7,5,FALSE) -> 8.2 | N13: =VLOOKUP(B13,Lookup!$A$2:$G$7,6,FALSE) -> 39 | O13: =VLOOKUP(B13,Lookup!$A$2:$G$7,7,FALSE) -> 1.2 | P13: =IF(AND(ISNUMBER(N13),ISNUMBER(O13)),N13/O13,"TBC") -> 32.5 | Q13: =IF(AND(ISNUMBER(N13),ISNUMBER(O13),ISNUMBER(M13)),((N13/O13)-M13)/(N13/O13),"TBC") -> 0.74769231 | R13: Re:Born Cashmere Fingerless Gloves, Yellow, O/S
A14: 900236ZZBEIG0000 | B14: =VALUE(LEFT(A14,6)) -> 900236 | C14: =MID(A14,9,4) -> BEIG | D14: =B14&C14 -> 900236BEIG | E14: =VLOOKUP(B14,Lookup!$A$2:$G$7,2,FALSE) -> Fingerless Gloves | F14: =VLOOKUP(B14,Lookup!$A$2:$G$7,3,FALSE) -> Cashmere | G14: ="Cashmere "&E14 -> Cashmere Fingerless Gloves | H14: TBC | I14: =TRIM(MID(R14,FIND(",",R14)+1,FIND(",",R14,FIND(",",R14)+1)-FIND(",",R14)-1)) -> Beige | J14: One Size | K14: =VLOOKUP(B14,Lookup!$A$2:$G$7,4,FALSE)&", "&I14&", O/S" -> Re:Born Cashmere Fingerless Gloves, Beige, O/S | L14: 624 | M14: =VLOOKUP(B14,Lookup!$A$2:$G$7,5,FALSE) -> 8.2 | N14: =VLOOKUP(B14,Lookup!$A$2:$G$7,6,FALSE) -> 39 | O14: =VLOOKUP(B14,Lookup!$A$2:$G$7,7,FALSE) -> 1.2 | P14: =IF(AND(ISNUMBER(N14),ISNUMBER(O14)),N14/O14,"TBC") -> 32.5 | Q14: =IF(AND(ISNUMBER(N14),ISNUMBER(O14),ISNUMBER(M14)),((N14/O14)-M14)/(N14/O14),"TBC") -> 0.74769231 | R14: Re:Born Cashmere Fingerless Gloves, Beige, O/S
... A52: 900231ZZMADD0000 | B52: =VALUE(LEFT(A52,6)) -> 900231 | C52: =MID(A52,9,4) -> MADD | D52: =B52&C52 -> 900231MADD | E52: =VLOOKUP(B52,Lookup!$A$2:$G$7,2,FALSE) -> Reversible Beanie | F52: =VLOOKUP(B52,Lookup!$A$2:$G$7,3,FALSE) -> Cashmere | G52: ="Cashmere "&E52 -> Cashmere Reversible Beanie | H52: TBC | I52: =TRIM(MID(R52,FIND(",",R52)+1,FIND(",",R52,FIND(",",R52)+1)-FIND(",",R52)-1)) -> Maroon And Dark Brown | J52: One Size | K52: =VLOOKUP(B52,Lookup!$A$2:$G$7,4,FALSE)&", "&I52&", O/S" -> Re:Born Reversible Cashmere Beanie, Maroon And Dark Brown, O/S | L52: 135 | M52: =VLOOKUP(B52,Lookup!$A$2:$G$7,5,FALSE) -> 9.1 | N52: =VLOOKUP(B52,Lookup!$A$2:$G$7,6,FALSE) -> 39 | O52: =VLOOKUP(B52,Lookup!$A$2:$G$7,7,FALSE) -> 1.2 | P52: =IF(AND(ISNUMBER(N52),ISNUMBER(O52)),N52/O52,"TBC") -> 32.5 | Q52: =IF(AND(ISNUMBER(N52),ISNUMBER(O52),ISNUMBER(M52)),((N52/O52)-M52)/(N52/O52),"TBC") -> 0.72 | R52: Re:Born Reverse Cashmere Beanie, Maroon And Dark Brown, O/S

Sheet Lookup
A1: Style Code | B1: Category | C1: Material | D1: Brand + Product Name | E1: Cost Price | F1: RRP | G1: Vat
A2: 900231 | B2: Reversible Beanie | C2: Cashmere | D2: Re:Born Reversible Cashmere Beanie | E2: 9.1 | F2: 39 | G2: 1.2
A3: 900232 | B3: Reversible Snood | C3: Cashmere | D3: Re:Born Reversible Cashmere Snood | E3: 9.1 | F3: 42 | G3: 1.2
A4: 900233 | B4: Snood & Glove Set | C4: Cashmere | D4: Re:Born Snood & Glove Set | E4: 17.2 | F4: TBC | G4: 1.2
A5: 900234 | B5: Beanie & Glove Set | C5: Cashmere | D5: Re:Born Beanie & Glove Set | E5: 17.2 | F5: TBC | G5: 1.2
A6: 900235 | B6: 2 Pack Gloves | C6: Cashmere | D6: Re:Born 2 Pack Gloves | E6: TBC | F6: TBC | G6: TBC
A7: 900236 | B7: Fingerless Gloves | C7: Cashmere | D7: Re:Born Cashmere Fingerless Gloves | E7: 8.2 | F7: 39 | G7: 1.2
A9: Style Code = first 6 digits of the Sku.
A10: '2 Pack Gloves' has no matching entry on the original ReBorn reference tab - pricing unknown, needs confirming.
A11: RRP for the two 'Set' product lines is shown as '?' on the original ReBorn reference tab - genuinely unconfirmed.

Sheet ReBorn
A1: Description | B1: Cost Price | C1: RRP | D1: Vat | E1: Country of Origin
A2: Re:Born Cashmere Headband | B2: 7.1 | C2: 25 | D2: 1.2 | E2: Dubai
A3: Re:Born Reversible Cashmere Beanie | B3: 9.1 | C3: 39 | D3: 1.2 | E3: Dubai
A4: Re:Born Reversible Cashmere Snood | B4: 9.1 | C4: 42 | D4: 1.2 | E4: Dubai
A5: Re:Born Snood & Glove Set | B5: 17.2 | C5: ? | D5: 1.2 | E5: Dubai
A6: Re:Born Beanie & Glove Set | B6: 17.2 | C6: ? | D6: 1.2 | E6: Dubai
A7: Re:Born Cashmere Fingerless Gloves | B7: 8.2 | C7: 39 | D7: 1.2 | E7: Dubai

Sheet Summary
A1: Re:Born Stock List - Summary Answers
A3: Q1. Total stock at net value | B3: =SUMPRODUCT(N('Data Sheet'!P3:P52),'Data Sheet'!L3:L52) -> 967677.5
A4: Of which, units excluded (price not yet confirmed - see Cleaning Log) | B4: =SUMPRODUCT((('Data Sheet'!P3:P52="TBC"))*'Data Sheet'!L3:L52) -> 321
A6: Q2. Fingerless Gloves currently in stock | B6: =SUMIF('Data Sheet'!E3:E52,"Fingerless Gloves",'Data Sheet'!L3:L52) -> 29118
A8: Stock quantity by category (reference)
A9: Fingerless Gloves | B9: =SUMIF('Data Sheet'!E3:E52,"Fingerless Gloves",'Data Sheet'!L3:L52) -> 29118
A10: Reversible Beanie | B10: =SUMIF('Data Sheet'!E3:E52,"Reversible Beanie",'Data Sheet'!L3:L52) -> 241
A11: Reversible Snood | B11: =SUMIF('Data Sheet'!E3:E52,"Reversible Snood",'Data Sheet'!L3:L52) -> 386
A12: Snood & Glove Set | B12: =SUMIF('Data Sheet'!E3:E52,"Snood & Glove Set",'Data Sheet'!L3:L52) -> 35
A13: Beanie & Glove Set | B13: =SUMIF('Data Sheet'!E3:E52,"Beanie & Glove Set",'Data Sheet'!L3:L52) -> 147
A14: 2 Pack Gloves | B14: =SUMIF('Data Sheet'!E3:E52,"2 Pack Gloves",'Data Sheet'!L3:L52) -> 139
A16: Notes:
A17: Net value = Quantity Available x Net RRP, summed across all rows with a confirmed RRP.
A18: 35 (Snood & Glove Set) + 147 (Beanie & Glove Set) + 139 (2 Pack Gloves) = 321 units are excluded
A19: from the net-value total because their RRP is not yet confirmed (see 'Cleaning Log' tab).
A20: All figures are live formulas that recalculate automatically from the 'Data Sheet' and 'Lookup' tabs.

Sheet Cleaning Log
A1: Data Cleaning Log - Re:Born Stock List
A3: Original Row(s) | B3: Issue Found | C3: Resolution | D3: Type
A4: Row 41 | B4: Completely blank row in the middle of the sheet. | C4: Row removed. | D4: Blank row
A5: Rows 4 & 5 | B5: Sku 900236ZZLGRY0000 listed twice with identical qty (3605) and identical description. | C5: Kept row 4, removed the exact duplicate. | D5: Exact duplicate
A6: Rows 6 & 7 | B6: Sku 900236ZZDKGR0000 listed twice with identical qty (3599) and identical description. | C6: Kept row 6, removed the exact duplicate. | D6: Exact duplicate
A7: Rows 58 & 59 | B7: Sku 900236ZZAAAI0000 (Teal) listed twice with identical qty (138) and identical description. | C7: Kept row 58, removed the exact duplicate. | D7: Exact duplicate
A8: Rows 17 & 18 | B8: Sku 900236ZZDMAA0000 listed twice, same qty (598), but row 18's description drops the word 'Fingerless' and uses 'One Size' instead of 'O/S'. | C8: Kept row 17 (matches the standard description format used everywhere else), removed row 18. | D8: Duplicate - inconsistent wording
A9: Rows 30 & 31 | B9: Sku 900235ZZBCAA0000 listed twice, same qty (41); row 31 spells the brand 'RE:Born' (wrong capitalisation) instead of 'Re:Born'. | C9: Kept row 30, removed the typo duplicate. | D9: Duplicate - typo
A10: Rows 36 & 47 | B10: Sku 900232ZZBGAA0000 listed twice (not adjacent - easy to miss), same qty (11); row 36 has a double space and is 8 rows away from its duplicate at row 47. | C10: Kept row 47, removed row 36. | D10: Duplicate - formatting/typo, non-adjacent
A11: Rows 37 & 38 | B11: Sku 900231ZZBLLL0000 listed twice, same qty (11); row 37 drops the word 'Cashmere' and has a double space. | C11: Kept row 38, removed row 37. | D11: Duplicate - inconsistent wording
A12: Rows 43 & 53 | B12: Sku 900231ZZBPAA0000 listed twice, same qty (49), 10 rows apart; row 53 misspells the brand as 'Re:Bron'. | C12: Kept row 43, removed row 53. | D12: Duplicate - typo, non-adjacent
A13: All Reversible Beanie rows | B13: Product name inconsistently written as 'Reverse Beanie' / 'Reverse Cashmere Beanie' in some rows vs 'Reversible Cashmere Beanie' in others. The ReBorn reference tab confirms 'Reversible' is correct. | C13: Standardised every row's Description to 'Re:Born Reversible Cashmere Beanie, <colour>, O/S'. | D13: Inconsistent naming
A14: Style Code / Colour Code / Option (cols B-D) | B14: Not filled in for any row except the example (row 2). Also, row 2's own Option (900196AUBE) does not actually match its own Style Code (900000) or Sku - the example itself contains an inconsistency. | C14: Derived Style Code and Colour Code directly from each Sku (first 6 digits / the 4 letters between 'ZZ' and the trailing '0000'), and built Option as Style Code + Colour Code consistently for every row. | D14: Missing data + example inconsistency
... A22: Range (col H) | B22: The row 2 example shows a Range of 'Core', but no other row, sheet, or column in the source data indicates what Range/Collection any product belongs to. | C22: Left as 'TBC' (highlighted) for every row rather than guessing. Recommend checking with merchandising for the correct Range per style. | D22: Further investigation needed
